nmc_met_base/__init__.py
nmc_met_base/arr.py
nmc_met_base/calculate.py
nmc_met_base/constants.py
nmc_met_base/css.py
nmc_met_base/cyclone.py
nmc_met_base/datetime.py
nmc_met_base/dynamic.py
nmc_met_base/ensemble.py
nmc_met_base/fast_barnes.py
nmc_met_base/filepath.py
nmc_met_base/geographical.py
nmc_met_base/geometry.py
nmc_met_base/grid.py
nmc_met_base/invert.py
nmc_met_base/math.py
nmc_met_base/mathfunc.py
nmc_met_base/moisture.py
nmc_met_base/numeric.py
nmc_met_base/oban.py
nmc_met_base/pressure.py
nmc_met_base/psi_phi.py
nmc_met_base/qpf_cal.py
nmc_met_base/regridding.py
nmc_met_base/sompy.py
nmc_met_base/spatial_interp.py
nmc_met_base/spectra.py
nmc_met_base/stats.py
nmc_met_base/thermal.py
nmc_met_base/thermofeel.py
nmc_met_base/time.py
nmc_met_base/topo.py
nmc_met_base/utilities.py
nmc_met_base/verify.py
nmc_met_base/wind.py
nmc_met_base/feature/cyclone.py
nmc_met_base/feature/cyclone_tracking.py
nmc_met_base/feature/strom_tracking.py
nmc_met_base-0.1.5.1.dist-info/LICENSE
nmc_met_base-0.1.5.1.dist-info/METADATA
nmc_met_base-0.1.5.1.dist-info/WHEEL
nmc_met_base-0.1.5.1.dist-info/top_level.txt
nmc_met_base-0.1.5.1.dist-info/RECORD
