Metadata-Version: 2.1
Name: nmc-met-base
Version: 0.1.5.1
Summary: A collections of basic functions for meteorological development.
Home-page: https://github.com/nmcdev/nmc_met_base
Author: The R & D Center for Weather Forecasting Technology in NMC, CMA
Author-email: kan.dai@foxmail.com
License: GPL3
Platform: all
Classifier: Development Status :: 4 - Beta
Classifier: Intended Audience :: Developers
Classifier: Intended Audience :: Science/Research
Classifier: License :: OSI Approved :: GNU General Public License v3 (GPLv3)
Classifier: Topic :: Scientific/Engineering
Classifier: Topic :: Scientific/Engineering :: Atmospheric Science
Classifier: Programming Language :: Python :: 3.7
Classifier: Programming Language :: Python :: 3.8
Classifier: Operating System :: POSIX :: Linux
Classifier: Operating System :: MacOS :: MacOS X
Classifier: Operating System :: Microsoft :: Windows
Requires-Python: >=3.6
License-File: LICENSE
Requires-Dist: numpy (>=1.17.0)
Requires-Dist: scipy (>=1.4.0)
Requires-Dist: pandas (>=1.0.0)
Requires-Dist: xarray (>=0.16.0)
Requires-Dist: pyproj (>=2.6.0)
Requires-Dist: python-dateutil (>=2.8.1)
Requires-Dist: numba (>=0.49.0)
Requires-Dist: metpy (>=0.12.0)
